nosauth/__init__.py
nosauth/all_certs.pem
nosauth/api.py
nosauth/test_generator.py
nosauth-0.1.5.dist-info/LICENSE
nosauth-0.1.5.dist-info/METADATA
nosauth-0.1.5.dist-info/WHEEL
nosauth-0.1.5.dist-info/top_level.txt
nosauth-0.1.5.dist-info/RECORD
