Metadata-Version: 2.1
Name: nosauth
Version: 0.1.5
Summary: Library that lets you obtain auth token so you can login to NosTale official servers
Home-page: https://github.com/morsisko/NosTale-Auth
Author: morsisko
License: MIT
Platform: UNKNOWN
Classifier: License :: OSI Approved :: MIT License
Classifier: Programming Language :: Python
Classifier: Programming Language :: Python :: 3
Classifier: Development Status :: 5 - Production/Stable
License-File: LICENSE
Requires-Dist: requests
